python_cptchnet/ImageCaptcha.py
python_cptchnet/ReCaptchaV2.py
python_cptchnet/config.py
python_cptchnet/decorators.py
python_cptchnet/errors.py
python_cptchnet/result_handler.py
python_cptchnet-0.2.dist-info/LICENSE
python_cptchnet-0.2.dist-info/METADATA
python_cptchnet-0.2.dist-info/WHEEL
python_cptchnet-0.2.dist-info/top_level.txt
python_cptchnet-0.2.dist-info/RECORD
